tfworker/__init__.py
tfworker/authenticators/__init__.py
tfworker/authenticators/aws.py
tfworker/authenticators/base.py
tfworker/authenticators/google.py
tfworker/backends/__init__.py
tfworker/backends/base.py
tfworker/backends/gcs.py
tfworker/backends/s3.py
tfworker/cli.py
tfworker/commands/__init__.py
tfworker/commands/base.py
tfworker/commands/clean.py
tfworker/commands/root.py
tfworker/commands/terraform.py
tfworker/commands/version.py
tfworker/constants.py
tfworker/definitions.py
tfworker/plugins.py
tfworker/providers/__init__.py
tfworker/providers/aws.py
tfworker/providers/base.py
tfworker/providers/generic.py
tfworker/providers/google.py
tfworker/providers/google_beta.py
tfworker/providers/helm.py
tfworker/util/__init__.py
tfworker/util/copier.py
tfworker/util/hcl2_transformer.py
tfworker/util/system.py
terraform_worker-0.10.9.dist-info/entry_points.txt
terraform_worker-0.10.9.dist-info/LICENSE
terraform_worker-0.10.9.dist-info/WHEEL
terraform_worker-0.10.9.dist-info/METADATA
terraform_worker-0.10.9.dist-info/RECORD
