Metadata-Version: 2.1
Name: terraform-worker
Version: 0.10.9
Summary: An orchestration tool for Terraform
Home-page: https://github.com/ephur/terraform-worker
License: Apache-2.0
Author: Richard Maynard
Author-email: richard.maynard@gmail.com
Requires-Python: >=3.7,<4.0
Classifier: Development Status :: 4 - Beta
Classifier: Environment :: Console
Classifier: Intended Audience :: Information Technology
Classifier: Intended Audience :: System Administrators
Classifier: License :: OSI Approved :: Apache Software License
Classifier: Natural Language :: English
Classifier: Operating System :: OS Independent
Classifier: Programming Language :: Python :: 3
Classifier: Programming Language :: Python :: 3.7
Classifier: Programming Language :: Python :: 3.8
Classifier: Programming Language :: Python :: 3.9
Classifier: Topic :: System :: Systems Administration
Requires-Dist: Sphinx (>=3.5.4,<4.0.0)
Requires-Dist: awscli (>=1.18.152,<2.0.0)
Requires-Dist: boto3 (>=1.15.8,<2.0.0)
Requires-Dist: click (>=7.1.2,<8.0.0)
Requires-Dist: google-cloud-storage (>=1.37.1,<2.0.0)
Requires-Dist: jinja2 (>=2.11.2,<3.0.0)
Requires-Dist: lark-parser (>=0.10.0,<0.11.0)
Requires-Dist: moto[sts] (>=2.0.5,<3.0.0)
Requires-Dist: python-hcl2 (>=2.0.3,<3.0.0)
Requires-Dist: pyyaml (>=5.4.1,<6.0.0)
Requires-Dist: requests (>=2.25,<3.0)
Requires-Dist: tenacity (>=6.2.0,<7.0.0)
Project-URL: Documentation, https://github.com/ephur/terraform-worker
Project-URL: Repository, https://github.com/ephur/terraform-worker
